{"otherData": {},"traceEvents":[{"cat":"function","dur":16,"name":"__cdecl L3gion::OpenGLTexture2D::~OpenGLTexture2D(void)","ph":"X","pid":0,"tid":1883008262,"ts":282919056917.600},{"cat":"function","dur":2,"name":"__cdecl L3gion::OpenGLShader::~OpenGLShader(void)","ph":"X","pid":0,"tid":1883008262,"ts":282919056997.800},{"cat":"function","dur":6,"name":"__cdecl L3gion::OpenGLVertexArray::~OpenGLVertexArray(void)","ph":"X","pid":0,"tid":1883008262,"ts":282919057031.300},{"cat":"function","dur":8,"name":"__cdecl L3gion::OpenGLIndexBuffer::~OpenGLIndexBuffer(void)","ph":"X","pid":0,"tid":1883008262,"ts":282919057061.000},{"cat":"function","dur":5,"name":"__cdecl L3gion::OpenGLVertexBuffer::~OpenGLVertexBuffer(void)","ph":"X","pid":0,"tid":1883008262,"ts":282919057092.400},{"cat":"function","dur":208,"name":"__cdecl L3gion::Application::~Application(void)","ph":"X","pid":0,"tid":1883008262,"ts":282919056915.300},{"cat":"function","dur":0,"name":"void __cdecl Sandbox2D::onDetach(void)","ph":"X","pid":0,"tid":1883008262,"ts":282919057144.300},{"cat":"function","dur":4,"name":"__cdecl L3gion::OpenGLTexture2D::~OpenGLTexture2D(void)","ph":"X","pid":0,"tid":1883008262,"ts":282919057164.900},{"cat":"function","dur":1143,"name":"void __cdecl L3gion::ImGuiLayer::onDetach(void)","ph":"X","pid":0,"tid":1883008262,"ts":282919057191.600},{"cat":"function","dur":27326,"name":"void __cdecl L3gion::WindowsWindow::shutdown(void)","ph":"X","pid":0,"tid":1883008262,"ts":282919058396.300},{"cat":"function","dur":27467,"name":"__cdecl L3gion::WindowsWindow::~WindowsWindow(void)","ph":"X","pid":0,"tid":1883008262,"ts":282919058396.100}]}