{"otherData": {},"traceEvents":[{"cat":"function","dur":38505,"name":"GLFW_Init","ph":"X","pid":0,"tid":284159362,"ts":291337955733.000},{"cat":"function","dur":301985,"name":"GLFW_CreateWindow","ph":"X","pid":0,"tid":284159362,"ts":291337994485.100},{"cat":"function","dur":3551,"name":"void L3gion::OpenGLContext::init(void)","ph":"X","pid":0,"tid":284159362,"ts":291338297183.600},{"cat":"function","dur":21,"name":"void L3gion::WindowsWindow::setVSync(bool)","ph":"X","pid":0,"tid":284159362,"ts":291338300823.300},{"cat":"function","dur":345694,"name":"void L3gion::WindowsWindow::init(const struct L3gion::WindowProps &)","ph":"X","pid":0,"tid":284159362,"ts":291337955178.700},{"cat":"function","dur":34,"name":"void L3gion::OpenGLRendererAPI::init(void)","ph":"X","pid":0,"tid":284159362,"ts":291338300899.400},{"cat":"function","dur":45,"name":"L3gion::OpenGLVertexArray::OpenGLVertexArray(void)","ph":"X","pid":0,"tid":284159362,"ts":291338300958.500},{"cat":"function","dur":53,"name":"L3gion::OpenGLVertexBuffer::OpenGLVertexBuffer(unsigned int)","ph":"X","pid":0,"tid":284159362,"ts":291338301036.200},{"cat":"function","dur":1,"name":"void L3gion::OpenGLVertexBuffer::bind(void) const","ph":"X","pid":0,"tid":284159362,"ts":291338301143.800},{"cat":"function","dur":46,"name":"void L3gion::OpenGLVertexArray::addVertexBuffer(const class std::shared_ptr<class L3gion::VertexBuffer> &)","ph":"X","pid":0,"tid":284159362,"ts":291338301140.500},{"cat":"function","dur":174,"name":"L3gion::OpenGLIndexBuffer::OpenGLIndexBuffer(unsigned int *,unsigned int)","ph":"X","pid":0,"tid":284159362,"ts":291338304197.400},{"cat":"function","dur":2,"name":"void L3gion::OpenGLIndexBuffer::bind(void) const","ph":"X","pid":0,"tid":284159362,"ts":291338304498.800},{"cat":"function","dur":35,"name":"void L3gion::OpenGLVertexArray::setIndexBuffer(const class std::shared_ptr<class L3gion::IndexBuffer> &)","ph":"X","pid":0,"tid":284159362,"ts":291338304495.400},{"cat":"function","dur":7,"name":"L3gion::OpenGLVertexArray::OpenGLVertexArray(void)","ph":"X","pid":0,"tid":284159362,"ts":291338304576.400},{"cat":"function","dur":5,"name":"L3gion::OpenGLVertexBuffer::OpenGLVertexBuffer(unsigned int)","ph":"X","pid":0,"tid":284159362,"ts":291338304611.800},{"cat":"function","dur":1,"name":"void L3gion::OpenGLVertexBuffer::bind(void) const","ph":"X","pid":0,"tid":284159362,"ts":291338304663.700},{"cat":"function","dur":62,"name":"void L3gion::OpenGLVertexArray::addVertexBuffer(const class std::shared_ptr<class L3gion::VertexBuffer> &)","ph":"X","pid":0,"tid":284159362,"ts":291338304662.500},{"cat":"function","dur":1,"name":"void L3gion::OpenGLIndexBuffer::bind(void) const","ph":"X","pid":0,"tid":284159362,"ts":291338304774.500},{"cat":"function","dur":26,"name":"void L3gion::OpenGLVertexArray::setIndexBuffer(const class std::shared_ptr<class L3gion::IndexBuffer> &)","ph":"X","pid":0,"tid":284159362,"ts":291338304773.700},{"cat":"function","dur":39,"name":"L3gion::OpenGLTexture2D::OpenGLTexture2D(unsigned int,unsigned int)","ph":"X","pid":0,"tid":284159362,"ts":291338305246.000},{"cat":"function","dur":10,"name":"void L3gion::OpenGLTexture2D::setData(void *,unsigned int)","ph":"X","pid":0,"tid":284159362,"ts":291338305322.300},{"cat":"function","dur":5156,"name":"class std::basic_string<char,struct std::char_traits<char>,class std::allocator<char> > L3gion::OpenGLShader::readFile(const class std::basic_string<char,struct std::char_traits<char>,class std::allocator<char> > &)","ph":"X","pid":0,"tid":284159362,"ts":291338305495.000},{"cat":"function","dur":24,"name":"class std::unordered_map<unsigned int,class std::basic_string<char,struct std::char_traits<char>,class std::allocator<char> >,struct std::hash<unsigned int>,struct std::equal_to<unsigned int>,class std::allocator<struct std::pair<unsigned int const ,class std::basic_string<char,struct std::char_traits<char>,class std::allocator<char> > > > > L3gion::OpenGLShader::preProcess(const class std::basic_string<char,struct std::char_traits<char>,class std::allocator<char> > &)","ph":"X","pid":0,"tid":284159362,"ts":291338310714.700},{"cat":"function","dur":29323,"name":"L3gion::OpenGLShader::OpenGLShader(const class std::basic_string<char,struct std::char_traits<char>,class std::allocator<char> > &)","ph":"X","pid":0,"tid":284159362,"ts":291338305387.200},{"cat":"function","dur":4416,"name":"class std::basic_string<char,struct std::char_traits<char>,class std::allocator<char> > L3gion::OpenGLShader::readFile(const class std::basic_string<char,struct std::char_traits<char>,class std::allocator<char> > &)","ph":"X","pid":0,"tid":284159362,"ts":291338334904.300},{"cat":"function","dur":23,"name":"class std::unordered_map<unsigned int,class std::basic_string<char,struct std::char_traits<char>,class std::allocator<char> >,struct std::hash<unsigned int>,struct std::equal_to<unsigned int>,class std::allocator<struct std::pair<unsigned int const ,class std::basic_string<char,struct std::char_traits<char>,class std::allocator<char> > > > > L3gion::OpenGLShader::preProcess(const class std::basic_string<char,struct std::char_traits<char>,class std::allocator<char> > &)","ph":"X","pid":0,"tid":284159362,"ts":291338339385.300},{"cat":"function","dur":26261,"name":"L3gion::OpenGLShader::OpenGLShader(const class std::basic_string<char,struct std::char_traits<char>,class std::allocator<char> > &)","ph":"X","pid":0,"tid":284159362,"ts":291338334818.000},{"cat":"function","dur":60396,"name":"void L3gion::Renderer2D::init(void)","ph":"X","pid":0,"tid":284159362,"ts":291338300954.500},{"cat":"function","dur":60509,"name":"void L3gion::Renderer::init(void)","ph":"X","pid":0,"tid":284159362,"ts":291338300898.500},{"cat":"function","dur":8565,"name":"void L3gion::ImGuiLayer::onAttach(void)","ph":"X","pid":0,"tid":284159362,"ts":291338361434.900},{"cat":"function","dur":8651,"name":"void L3gion::Application::pushOverlay(class L3gion::Layer *)","ph":"X","pid":0,"tid":284159362,"ts":291338361432.000},{"cat":"function","dur":414935,"name":"L3gion::Application::Application(const class std::basic_string<char,struct std::char_traits<char>,class std::allocator<char> > &,struct L3gion::ApplicationCommandLineArgs)","ph":"X","pid":0,"tid":284159362,"ts":291337955171.700},{"cat":"function","dur":1709,"name":"stbi_load - OpenGLTexture2D::OpenGLTexture2D(const std::string&)","ph":"X","pid":0,"tid":284159362,"ts":291338370275.400},{"cat":"function","dur":1841,"name":"L3gion::OpenGLTexture2D::OpenGLTexture2D(const class std::basic_string<char,struct std::char_traits<char>,class std::allocator<char> > &)","ph":"X","pid":0,"tid":284159362,"ts":291338370275.000},{"cat":"function","dur":1168,"name":"stbi_load - OpenGLTexture2D::OpenGLTexture2D(const std::string&)","ph":"X","pid":0,"tid":284159362,"ts":291338372160.500},{"cat":"function","dur":1276,"name":"L3gion::OpenGLTexture2D::OpenGLTexture2D(const class std::basic_string<char,struct std::char_traits<char>,class std::allocator<char> > &)","ph":"X","pid":0,"tid":284159362,"ts":291338372160.300},{"cat":"function","dur":2051,"name":"void L3gion::ContentBrowserPanel::refresh(void)","ph":"X","pid":0,"tid":284159362,"ts":291338373480.000},{"cat":"function","dur":2294,"name":"stbi_load - OpenGLTexture2D::OpenGLTexture2D(const std::string&)","ph":"X","pid":0,"tid":284159362,"ts":291338375615.800},{"cat":"function","dur":2446,"name":"L3gion::OpenGLTexture2D::OpenGLTexture2D(const class std::basic_string<char,struct std::char_traits<char>,class std::allocator<char> > &)","ph":"X","pid":0,"tid":284159362,"ts":291338375615.500},{"cat":"function","dur":2337,"name":"stbi_load - OpenGLTexture2D::OpenGLTexture2D(const std::string&)","ph":"X","pid":0,"tid":284159362,"ts":291338378107.300},{"cat":"function","dur":2463,"name":"L3gion::OpenGLTexture2D::OpenGLTexture2D(const class std::basic_string<char,struct std::char_traits<char>,class std::allocator<char> > &)","ph":"X","pid":0,"tid":284159362,"ts":291338378107.100},{"cat":"function","dur":5142,"name":"void L3gion::EditorLayer::onAttach(void)","ph":"X","pid":0,"tid":284159362,"ts":291338375611.600},{"cat":"function","dur":5178,"name":"void L3gion::Application::pushLayer(class L3gion::Layer *)","ph":"X","pid":0,"tid":284159362,"ts":291338375604.400},{"cat":"function","dur":19,"name":"void L3gion::WindowsWindow::setVSync(bool)","ph":"X","pid":0,"tid":284159362,"ts":291338380806.000}]}